z3c/batching/README.rst
z3c/batching/__init__.py
z3c/batching/batch.py
z3c/batching/configure.zcml
z3c/batching/interfaces.py
z3c/batching/subset.py
z3c/batching/subset.rst
z3c/batching/tests.py
z3c_batching-4.0.dist-info/LICENSE.txt
z3c_batching-4.0.dist-info/METADATA
z3c_batching-4.0.dist-info/WHEEL
z3c_batching-4.0.dist-info/top_level.txt
z3c_batching-4.0.dist-info/RECORD
